{
  "DIBAO_STANDARD": {
    "上海": 1650,
    "北京": 1395,
    "天津": 1010,
    "重庆": 800,
    "广东（深圳）": 1563,
    "广东（广州）": 1327,
    "广东（珠海）": 1260,
    "广东（东莞）": 1260,
    "广东（中山）": 1225,
    "广东（佛山）": 1226,
    "广东（惠州）": 932,
    "广东（江门）": 932,
    "广东（肇庆）": 932,
    "广东（梅州）": 862,
    "广东（清远）": 913,
    "广东（揭阳）": 920,
    "广东（汕头）": 869,
    "广东（韶关）": 869,
    "广东（河源）": 869,
    "广东（汕尾）": 869,
    "广东（阳江）": 869,
    "广东（湛江）": 869,
    "广东（茂名）": 869,
    "广东（潮州）": 869,
    "广东（云浮）": 869,
    "浙江（杭州）": 1310,
    "浙江（宁波）": 1310,
    "浙江（温州）": 1190,
    "浙江（嘉兴）": 1190,
    "浙江（湖州）": 1190,
    "浙江（绍兴）": 1190,
    "浙江（金华）": 1190,
    "浙江（衢州）": 1190,
    "浙江（舟山）": 1190,
    "浙江（台州）": 1190,
    "浙江（丽水）": 1190,
    "江苏（苏州）": 1208,
    "江苏（无锡）": 1167,
    "江苏（南京）": 1115,
    "江苏（常州）": 1080,
    "江苏（镇江）": 926,
    "江苏（扬州）": 893,
    "江苏（南通）": 885,
    "江苏（泰州）": 877,
    "江苏（盐城）": 828,
    "江苏（徐州）": 813,
    "江苏（连云港）": 738,
    "江苏（淮安）": 733,
    "江苏（宿迁）": 685,
    "福建（厦门）": 1200,
    "福建（福州）": 970,
    "福建（泉州石狮）": 940,
    "福建（泉州鲤城等6区市）": 900,
    "福建（泉州安溪等3县）": 845,
    "福建（漳州芗城龙文）": 941,
    "福建（漳州其余县市）": 869,
    "福建（莆田）": 900,
    "福建（三明三元沙县永安）": 872,
    "福建（三明其他8县）": 806,
    "福建（南平延平建阳邵武武夷山建瓯）": 872,
    "福建（南平顺昌浦城光泽松溪政和）": 806,
    "福建（龙岩新罗区）": 872,
    "福建（龙岩其他6县市）": 806,
    "福建（宁德蕉城福安福鼎）": 866,
    "福建（宁德古田屏南周宁寿宁柘荣霞浦）": 799,
    "山东（济南）": 1114,
    "山东（青岛）": 1115,
    "山东（东营）": 1075,
    "山东（烟台）": 1069,
    "山东（威海）": 1062,
    "山东（滨州）": 1070,
    "山东（潍坊）": 1003,
    "山东（淄博）": 989,
    "山东（济宁）": 993,
    "山东（日照）": 977,
    "山东（泰安）": 980,
    "山东（德州）": 956,
    "山东（枣庄）": 941,
    "山东（菏泽）": 939,
    "山东（聊城）": 931,
    "山东（临沂）": 932,
    "安徽（合肥）": 1009,
    "安徽（芜湖）": 918,
    "安徽（马鞍山）": 907,
    "安徽（黄山）": 851,
    "安徽（淮南）": 842,
    "安徽（宣城）": 842,
    "安徽（铜陵）": 835,
    "安徽（蚌埠）": 831,
    "安徽（池州）": 811,
    "安徽（滁州）": 810,
    "安徽（安庆）": 798,
    "安徽（淮北）": 795,
    "安徽（阜阳）": 781,
    "安徽（宿州）": 780,
    "安徽（亳州）": 779,
    "安徽（六安）": 779,
    "湖北（武汉）": 1070,
    "湖北（宜昌）": 880,
    "湖北（荆州中心城区）": 880,
    "湖北（襄阳樊城区）": 818,
    "湖北（黄冈）": 729,
    "湖南（长沙）": 770,
    "湖南（株洲）": 740,
    "湖南（湘潭）": 740,
    "湖南（衡阳）": 740,
    "湖南（岳阳）": 740,
    "湖南（常德）": 740,
    "湖南（益阳）": 740,
    "湖南（郴州）": 740,
    "湖南（永州）": 740,
    "湖南（怀化）": 740,
    "湖南（娄底）": 740,
    "湖南（邵阳）": 740,
    "湖南（湘西州）": 740,
    "湖南": 740,
    "河南（郑州）": 841,
    "河南（洛阳）": 823,
    "河南（开封）": 729,
    "河南（驻马店）": 698,
    "河南（周口）": 697,
    "河南（安阳）": 692,
    "河南（焦作）": 719,
    "河南（商丘）": 702,
    "河南（新乡）": 697,
    "河南（南阳）": 697,
    "河南（平顶山）": 697,
    "河南（信阳）": 692,
    "河南（许昌）": 700,
    "江西": 980,
    "四川（成都区）": 990,
    "四川（成都县市）": 950,
    "四川（攀枝花）": 880,
    "四川（绵阳）": 869,
    "四川（德阳）": 840,
    "四川（宜宾）": 830,
    "四川（自贡）": 828,
    "四川": 826,
    "河北（廊坊三河大厂香河）": 1006,
    "河北（廊坊广阳安次固安开发区）": 914,
    "河北（廊坊永清霸州文安大城）": 870,
    "河北（唐山一类）": 910,
    "河北（唐山二类）": 884,
    "河北（唐山三类）": 858,
    "河北（石家庄一档）": 860,
    "河北（石家庄二档）": 850,
    "河北（石家庄三档）": 840,
    "河北（保定）": 779,
    "河北（邯郸）": 833,
    "辽宁（大连）": 925,
    "辽宁（盘锦）": 808,
    "辽宁（鞍山）": 794,
    "辽宁（沈阳）": 793,
    "辽宁（锦州）": 778,
    "辽宁（丹东）": 770,
    "辽宁（阜新）": 753,
    "辽宁（铁岭）": 744,
    "辽宁（辽阳）": 730,
    "辽宁（朝阳）": 728,
    "辽宁（葫芦岛）": 727,
    "辽宁（本溪）": 761,
    "辽宁（营口）": 757,
    "吉林（长春）": 760,
    "吉林（吉林市）": 760,
    "吉林（第一档）": 760,
    "吉林（第二档）": 710,
    "吉林（第三档）": 660,
    "吉林（第四档）": 610,
    "黑龙江（哈尔滨9区）": 870,
    "黑龙江（哈尔滨9县市）": 780,
    "黑龙江": 780,
    "山西（太原）": 820,
    "山西（大同平城区）": 730,
    "山西（大同其余区县）": 630,
    "山西（长治）": 722,
    "山西（晋中）": 680,
    "山西（运城）": 700,
    "山西": 669,
    "内蒙古（呼和浩特）": 918,
    "内蒙古（包头九原区）": 885,
    "内蒙古（鄂尔多斯）": 1020,
    "内蒙古（通辽）": 864,
    "内蒙古（呼伦贝尔）": 808,
    "内蒙古（赤峰）": 788,
    "内蒙古": 815,
    "陕西（西安）": 900,
    "陕西（咸阳）": 900,
    "陕西（宝鸡）": 728,
    "陕西（渭南）": 686,
    "甘肃（兰州5区）": 920,
    "甘肃（兰州3县）": 700,
    "甘肃（酒泉）": 715,
    "甘肃（天水）": 715,
    "甘肃": 700,
    "青海（西宁）": 763,
    "青海（海东）": 688,
    "青海（海北州）": 765,
    "青海（海南州）": 693,
    "青海（海西州）": 906,
    "青海（果洛州）": 915,
    "青海（黄南州）": 708,
    "青海（玉树州）": 708,
    "宁夏（银川）": 765,
    "宁夏（石嘴山）": 740,
    "宁夏（吴忠）": 740,
    "宁夏（固原）": 740,
    "宁夏（中卫）": 740,
    "宁夏": 740,
    "新疆": 770,
    "新疆（乌鲁木齐）": 770,
    "新疆（克拉玛依）": 770,
    "新疆（昌吉）": 770,
    "新疆（库尔勒）": 770,
    "新疆（喀什）": 770,
    "新疆（石河子）": 770,
    "贵州（贵阳）": 851,
    "贵州（第一档）": 851,
    "贵州（第二档）": 832,
    "贵州（第三档）": 779,
    "云南": 744,
    "广西（南宁）": 810,
    "海南": 850,
    "西藏": 1027
  },
  "NATIONAL_AVG": {
    "城市低保平均": 835,
    "农村低保平均": 623,
    "城市特困平均": 1175
  },
  "TEKUN_RATIO_DEFAULT": 1.3,
  "TEKUN_CITY_OVERRIDE": {
    "深圳": [
      2502,
      1.6
    ],
    "上海": [
      2145,
      1.3
    ],
    "北京": [
      1814,
      1.3
    ],
    "广州": [
      1725,
      1.3
    ],
    "重庆": [
      1001,
      1.25
    ],
    "江西": [
      1275,
      1.3
    ]
  },
  "TEKUN_CONDITIONS": "同时满足：① 无劳动能力（60 岁以上/未满 16 岁/一二级残疾）；② 无生活来源；③ 无法定义务人，或义务人无履行能力。",
  "DIBAO_EDGE_RATIO": 1.5,
  "DIBAO_EDGE_RATIO_MAX": 2.0,
  "DIBAO_EDGE_ASSISTANCE": [
    "医疗救助（资助参保、住院救助）",
    "教育救助（学费减免、助学金）",
    "住房救助（公租房优先、租金减免）",
    "就业救助（免费培训、公益岗位）",
    "临时救助（参照支出型标准）"
  ],
  "TEMP_RELIEF_MULTIPLE": {
    "轻急难型": [
      2,
      3
    ],
    "支出型（疾病）": [
      3,
      12
    ],
    "支出型（教育）": [
      2,
      6
    ],
    "重大困难（一事一议）": [
      12,
      null
    ]
  },
  "MEDICAL_ASSIST_TIERS": {
    "特困人员": {
      "资助参保": "全额",
      "起付线": "极低或取消",
      "报销比例": [
        0.9,
        1.0
      ]
    },
    "低保对象": {
      "资助参保": "全额/定额",
      "起付线": "降 50%",
      "报销比例": "提高 5~10%"
    },
    "低保边缘/监测人口": {
      "资助参保": "定额",
      "起付线": [
        3000,
        5000
      ],
      "报销比例": [
        0.6,
        0.7
      ]
    },
    "因病致贫重病患者": {
      "资助参保": "不资助",
      "起付线": [
        10000,
        20000
      ],
      "报销比例": "按比例救助"
    }
  },
  "PUBLIC_HOUSING": {
    "上海": {
      "户籍": "本地户籍；或居住证+1年劳动合同+社保",
      "收入上限": "无",
      "住房": "人均<15㎡",
      "租金": "低于市场 30~50%"
    },
    "北京": {
      "户籍": "本地户籍；非京籍需居住证+连续5年社保+≤45岁",
      "收入上限": "3口≤10万/年；4口≤13万/年",
      "住房": "人均使用面积≤15㎡",
      "租金": "16~72 元/㎡·月"
    },
    "深圳": {
      "户籍": "深户或居住证一定年限",
      "收入上限": "家庭年收入≤约20万",
      "住房": "无房",
      "租金": null
    },
    "广州": {
      "户籍": "本市户籍或稳定就业外来人员",
      "收入上限": "家庭年收入≤一定比例",
      "住房": "无房或<15㎡",
      "租金": null
    }
  },
  "PROPERTY_LIMIT": {
    "上海": {
      "金融资产人均": "≤5.94万（36个月低保）",
      "车辆": "禁机动车",
      "房产": "1套或无房"
    },
    "湖北": {
      "金融资产人均": "≤年低保×4倍",
      "车辆": "1辆≤12倍年低保",
      "房产": "≤人均1.5倍"
    },
    "山东": {
      "金融资产人均": "≤年低保×3倍",
      "车辆": "基本禁止",
      "房产": "≤保障面积×2倍"
    },
    "河南": {
      "金融资产人均": "≤年低保×3倍",
      "车辆": "可1辆(6倍内)",
      "房产": "≤人均1.2倍"
    },
    "陕西": {
      "金融资产人均": "≤上年人均可支配收入",
      "车辆": "≤年低保×5倍",
      "房产": "城市≤2套各≤90㎡"
    },
    "甘肃": {
      "金融资产人均": "≤低保×人口×24月",
      "车辆": "≤5万元",
      "房产": "1套+祖屋豁免"
    },
    "江西": {
      "金融资产人均": "≤上年人均可支配收入×2倍",
      "车辆": "严格禁止",
      "房产": "仅1套、无商铺"
    }
  },
  "PROPERTY_LIMIT_COMMON": {
    "金融资产": "人均不超过当地年低保 × 2~4 倍（各省不同）",
    "车辆": "不得拥有生活用机动车（残疾人代步车/谋生小经营车除外）",
    "房产": "仅 1 套自住房或无房；无商铺/办公楼"
  },
  "DIBAO_TIER_RANGE": {
    "一线": [
      1300,
      1650
    ],
    "新一线": [
      900,
      1300
    ],
    "二线": [
      800,
      1000
    ],
    "三线": [
      700,
      850
    ],
    "四线": [
      650,
      780
    ],
    "五线": [
      600,
      740
    ]
  },
  "PENDING_CITIES": {
    "河南": [
      "濮阳",
      "漯河",
      "三门峡",
      "鹤壁",
      "济源"
    ],
    "山西": [
      "阳泉",
      "晋城",
      "朔州",
      "忻州",
      "临汾",
      "吕梁"
    ],
    "内蒙古": [
      "巴彦淖尔",
      "乌兰察布",
      "锡林郭勒",
      "兴安",
      "阿拉善"
    ],
    "陕西": [
      "延安",
      "汉中",
      "榆林",
      "安康",
      "商洛",
      "铜川"
    ],
    "甘肃": [
      "张掖",
      "武威",
      "定西",
      "平凉",
      "庆阳",
      "陇南",
      "白银",
      "金昌",
      "嘉峪关"
    ],
    "广西": [
      "柳州",
      "桂林",
      "梧州",
      "北海",
      "防城港",
      "钦州",
      "贵港",
      "玉林",
      "百色",
      "贺州",
      "河池",
      "来宾",
      "崇左"
    ]
  }
}